sunse/__init__.py
sunse/__main__.py
sunse/comms/__init__.py
sunse/comms/list.py
sunse/comms/main.py
sunse/items/__init__.py
sunse/items/book.py
sunse/items/note.py
sunse/tools/__init__.py
sunse/tools/file.py
sunse/tools/path.py
sunse/tools/vals.py
sunse-0.1.0.dist-info/METADATA
sunse-0.1.0.dist-info/WHEEL
sunse-0.1.0.dist-info/entry_points.txt
sunse-0.1.0.dist-info/top_level.txt
sunse-0.1.0.dist-info/RECORD
