Metadata-Version: 2.1
Name: sunse
Version: 0.1.0
Summary: A plaintext note manager CLI in Python 3.10.
Author-email: Stephen Malone <none@example.com>
License: BSD 3-Clause License
Project-URL: Homepage, https://github.com/wirehaiku/Sunse
Project-URL: Tracker, https://github.com/wirehaiku/Sunse/issues
Keywords: notes,note-taking,cli
Classifier: Development Status :: 3 - Alpha
Classifier: Intended Audience :: End Users/Desktop
Classifier: License :: OSI Approved :: BSD License
Classifier: Programming Language :: Python :: 3 :: Only
Classifier: Programming Language :: Python :: 3.10
Classifier: Topic :: Office/Business
Requires-Python: >=3.10
Requires-Dist: click (>=8.1)
Provides-Extra: test
Requires-Dist: mypy (>=1.1) ; extra == 'test'
Requires-Dist: pytest (>=7.2) ; extra == 'test'
Requires-Dist: pytest-mypy (>=0.10) ; extra == 'test'
